namedtuple_from_dict/LICENSE
namedtuple_from_dict/README.MD
namedtuple_from_dict/__init__.py
namedtuple_from_dict/requirements.txt
namedtuple_from_dict/thirdparty.json
namedtuple_from_dict-0.10.dist-info/LICENSE.rst
namedtuple_from_dict-0.10.dist-info/METADATA
namedtuple_from_dict-0.10.dist-info/WHEEL
namedtuple_from_dict-0.10.dist-info/top_level.txt
namedtuple_from_dict-0.10.dist-info/RECORD
